VMdesign.v
module vending_machine_2503(
    input clk,
    input rst,
    input [1:0] in,   // 01 = 5rs, 10 = 10rs
    output reg out,
    output reg [1:0] change
);

parameter s0 = 2'b00;
parameter s1 = 2'b01;
parameter s2 = 2'b10;

reg [1:0] c_state, n_state;

always @(posedge clk or posedge rst) begin
    if (rst)
        c_state <= s0;
    else
        c_state <= n_state;
end

// Combinational block: next state and outputs
always @(*) begin
    n_state = c_state;
    out = 0;
    change = 2'b00;

    case (c_state)
        s0: begin
            if (in == 2'b00)
                n_state = s0;
            else if (in == 2'b01)
                n_state = s1;
            else if (in == 2'b10)
                n_state = s2;
        end

        s1: begin
            if (in == 2'b00) begin
                n_state = s0;
                change = 2'b01;   // return 5
            end
            else if (in == 2'b01)
                n_state = s2;
            else if (in == 2'b10) begin
                n_state = s0;
                out = 1;
            end
        end

        s2: begin
            if (in == 2'b00) begin
                n_state = s0;
                change = 2'b10;   // return 10
            end
            else if (in == 2'b01) begin
                n_state = s0;
                out = 1;
            end
            else if (in == 2'b10) begin
                n_state = s0;
                out = 1;
                change = 2'b01;   // return 5
            end
        end

        default: begin
            n_state = s0;
            out = 0;
            change = 2'b00;
        end
    endcase
end

endmodule

VM_tb.v
module vending_machine_tb;
  
  //inputs
  reg clk;
  reg[1:0] in;
  reg rst;
  
  //output
  wire out;
  wire[1:0] change;
  
  vending_machine_2503 uut(
    .clk(clk),
    .rst(rst),
    .in(in),
    .out(out),
    .change(change)
  );
  
  initial begin
    
    //initialise inputs
    $dumpfile("vending_machine.vcd");
    $dumpvars(0,vending_machine_tb);

    clk = 0;
    rst = 1;
    in  = 2'b00;

    #5 rst = 0;

    #5  in = 2'b01;   // first 5
    #10 in = 2'b01;   // second 5
    #10 in = 2'b01;   // third 5 => vend
    #10 in = 2'b00;   // no coin now

    #20 $finish;
  end
  always #4 clk = ~clk;
  
endmodule

vending_machine.vcd
$date
	Sat Mar 14 10:12:32 2026
$end
$version
	Icarus Verilog
$end
$timescale
	1s
$end
$scope module vending_machine_tb $end
$var wire 1 ! out $end
$var wire 2 " change [1:0] $end
$var reg 1 # clk $end
$var reg 2 $ in [1:0] $end
$var reg 1 % rst $end
$scope module uut $end
$var wire 1 # clk $end
$var wire 2 & in [1:0] $end
$var wire 1 % rst $end
$var parameter 2 ' s0 $end
$var parameter 2 ( s1 $end
$var parameter 2 ) s2 $end
$var reg 2 * c_state [1:0] $end
$var reg 2 + change [1:0] $end
$var reg 2 , n_state [1:0] $end
$var reg 1 ! out $end
$upscope $end
$upscope $end
$enddefinitions $end
$comment Show the parameter values. $end
$dumpall
b10 )
b1 (
b0 '
$end
#0
$dumpvars
b0 ,
b0 +
b0 *
b0 &
1%
b0 $
0#
b0 "
0!
$end
#4
1#
#5
0%
#8
0#
#10
b1 ,
b1 $
b1 &
#12
b10 ,
b1 *
1#
#16
0#
#20
1!
b0 ,
b10 *
1#
#24
0#
#28
b1 ,
0!
b0 *
1#
#32
0#
#36
b10 ,
b1 *
1#
#40
b1 "
b1 +
b0 ,
0#
b0 $
b0 &
#44
b0 "
b0 +
b0 *
1#
